dlblocks/Augmentation.py
dlblocks/Cache.py
dlblocks/HTMLReport.py
dlblocks/NumpyUtils.py
dlblocks/PlotUtils.py
dlblocks/PytorchUtils.py
dlblocks/SegUtils.py
dlblocks/Segmentation.py
dlblocks/TrainUtils.py
dlblocks/VisPytorch.py
dlblocks/__init__.py
dlblocks/caffe_utils.py
dlblocks/dataset_utils.py
dlblocks/image.py
dlblocks/juprun.py
dlblocks/keras_utils.py
dlblocks/misc.py
dlblocks/pytorch_interface.py
dlblocks/pyutils.py
dlblocks/text.py
dlblocks-0.1.dist-info/DESCRIPTION.rst
dlblocks-0.1.dist-info/METADATA
dlblocks-0.1.dist-info/RECORD
dlblocks-0.1.dist-info/WHEEL
dlblocks-0.1.dist-info/metadata.json
dlblocks-0.1.dist-info/top_level.txt
