Metadata-Version: 2.0
Name: dlblocks
Version: 0.1
Summary: Contains a lot of util libraries used across projects
Home-page: http://github.com/github/repo
Author: John Doe
Author-email: authoremail@mail.com
License: BSD
Platform: any
